dqm/.DS_Store
dqm/__init__.py
dqm-0.0.9.dist-info/METADATA
dqm-0.0.9.dist-info/WHEEL
dqm-0.0.9.dist-info/licenses/LICENSE
dqm-0.0.9.dist-info/RECORD
